{
	"entity-type":"ZOMBIE",
	"prefix":"Undead",
	"name":"Miner",
	"main-hand":"101",
	"melee-defense":"12.6",
	"ranged-defense":"18.9",
	"magic-defense":"6.3",
	"melee-strength":"0.75",
	"health":"12",
	"melee-accuracy":"75.6",
	"wander-radius":"15",
	"respawn-delay":"600",
	"locations":[
		{
			"world":"world",
			"x":"4528.5",
			"y":"56",
			"z":"-8590.5",
		},
		{
			"world":"world",
			"x":"4531.5",
			"y":"56",
			"z":"-8577.5",
		},
		{
			"world":"world",
			"x":"4541.5",
			"y":"56",
			"z":"-8576.5",
		},
		{
			"world":"world",
			"x":"4542.5",
			"y":"56",
			"z":"-8589.5",
		}
	],
	"drop-tables":[
		[
			{
				"item-id":"101",
				"weight":"1"
			},
			{
				"item-id":"113",
				"weight":"1"
			},
			{
				"item-id":"109",
				"weight":"1"
			}
		],
		[
			{
				"item-id":"702",
				"weight":"1"
			}	
		]
	]



}
